README.md
setup.py
Flask_SES_Mailer.egg-info/PKG-INFO
Flask_SES_Mailer.egg-info/SOURCES.txt
Flask_SES_Mailer.egg-info/dependency_links.txt
Flask_SES_Mailer.egg-info/not-zip-safe
Flask_SES_Mailer.egg-info/requires.txt
Flask_SES_Mailer.egg-info/top_level.txt
flask_ses_mailer/__init__.py