Metadata-Version: 1.1
Name: Flask-SES-Mailer
Version: 1.0.2
Summary: Flask extension to send mail via AWS Simple Email Service.
Home-page: https://github.com/iamjohnnym/Flask-SES-Mailer
Author: john martin
Author-email: john.martin@configure.systems
License: Apache2
Platform: any
Classifier: Environment :: Web Environment
Classifier: Intended Audience :: Developers
Classifier: License :: OSI Approved :: BSD License
Classifier: Operating System :: OS Independent
Classifier: Programming Language :: Python
Classifier: Topic :: Internet :: WWW/HTTP :: Dynamic Content
Classifier: Topic :: Software Development :: Libraries :: Python Modules
